README
setup.py
asylum/__init__.py
asylum/__main__.py
asylum/capabilities.py
asylum/cgroups.py
asylum/conf.py
asylum/daemon.py
asylum/detect.py
asylum/mount.py
asylum/rlimits.py
asylum/syscall.py
asylum/utils.py
asylum.egg-info/PKG-INFO
asylum.egg-info/SOURCES.txt
asylum.egg-info/dependency_links.txt
asylum.egg-info/entry_points.txt
asylum.egg-info/requires.txt
asylum.egg-info/top_level.txt
asylum.egg-info/zip-safe