Metadata-Version: 1.1
Name: asylum
Version: 0.4
Summary: Lightweight containerization solution for Linux
Home-page: http://code.pocketnix.org/asylum
Author: Da_Blitz
Author-email: code@pocketnix.org
License: MIT BSD
Download-URL: http://code.pocketnix.org/asylum/archive/tip.tar.bz2
Keywords: linux virtual virtualistion LXC openVZ
Platform: UNKNOWN
Classifier: Programming Language :: Python :: 3
